{
   "agent": "Arduino Mega2560",
   "behavior": "OK",
   "behaviorClose": "OK",
   "case": 37,
   "closedByMe": false,
   "createStats": true,
   "createWirelog": true,
   "description": "Send small text message, then send frame with reserved non-control <b>Opcode = 5</b>, then send Ping.",
   "droppedByMe": false,
   "duration": 20,
   "expectation": "Echo for first message is received, but then connection is failed immediately, since reserved opcode frame is used. A Pong is not received.",
   "expected": {
      "NON-STRICT": [],
      "OK": [
         [
            "message",
            "Hello, world!",
            false
         ]
      ]
   },
   "expectedClose": {
      "closeCode": [
         1002
      ],
      "closedByMe": false,
      "requireClean": false
   },
   "failedByMe": false,
   "httpRequest": "GET / HTTP/1.1\r\nUser-Agent: AutobahnTestSuite/0.8.0-0.10.9\r\nHost: 192.168.46.179:3000\r\nUpgrade: WebSocket\r\nConnection: Upgrade\r\nPragma: no-cache\r\nCache-Control: no-cache\r\nSec-WebSocket-Key: VdNu7Qlgti98E7HAkDUL5Q==\r\nSec-WebSocket-Version: 13\r\n\r\n",
   "httpResponse": "HTTP/1.1 101 Switching Protocols\r\nUpgrade: websocket\r\nConnection: Upgrade\r\nSec-WebSocket-Accept: p0gUF3JB1PK4he5RDiYQkaL3SYA=\r\n\r\n",
   "id": "4.1.3",
   "isServer": false,
   "localCloseCode": 1000,
   "localCloseReason": null,
   "received": [
      [
         "message",
         "Hello, world!",
         false
      ]
   ],
   "remoteCloseCode": 1002,
   "remoteCloseReason": null,
   "reportCompressionRatio": false,
   "reportTime": false,
   "result": "Actual events match at least one expected.",
   "resultClose": "Connection was properly closed",
   "rxFrameStats": {
      "1": 1,
      "8": 1
   },
   "rxOctetStats": {
      "1": 4,
      "2": 4,
      "3": 4,
      "4": 6,
      "5": 1,
      "6": 1,
      "10": 1,
      "15": 1,
      "64": 1
   },
   "started": "2018-07-24T14:57:40.597Z",
   "trafficStats": null,
   "txFrameStats": {
      "1": 1,
      "5": 1,
      "8": 1,
      "9": 1
   },
   "txOctetStats": {
      "6": 2,
      "8": 1,
      "19": 1,
      "245": 1
   },
   "wasClean": true,
   "wasCloseHandshakeTimeout": false,
   "wasNotCleanReason": null,
   "wasOpenHandshakeTimeout": false,
   "wasServerConnectionDropTimeout": false,
   "wirelog": [
      [
         "TO",
         [
            245,
            "474554202f20485454502f312e310d0a557365722d4167656e743a204175746f6261686e5465737453756974652f302e382e302d302e31302e390d0a486f7374 ..."
         ],
         false
      ],
      [
         "RO",
         [
            3,
            "485454"
         ]
      ],
      [
         "RO",
         [
            3,
            "502f31"
         ]
      ],
      [
         "RO",
         [
            3,
            "2e3120"
         ]
      ],
      [
         "RO",
         [
            4,
            "31303120"
         ]
      ],
      [
         "RO",
         [
            4,
            "53776974"
         ]
      ],
      [
         "RO",
         [
            1,
            "63"
         ]
      ],
      [
         "RO",
         [
            4,
            "68696e67"
         ]
      ],
      [
         "RO",
         [
            3,
            "205072"
         ]
      ],
      [
         "RO",
         [
            2,
            "6f74"
         ]
      ],
      [
         "RO",
         [
            1,
            "6f"
         ]
      ],
      [
         "RO",
         [
            6,
            "636f6c730d0a"
         ]
      ],
      [
         "RO",
         [
            2,
            "5570"
         ]
      ],
      [
         "RO",
         [
            2,
            "6772"
         ]
      ],
      [
         "RO",
         [
            1,
            "61"
         ]
      ],
      [
         "RO",
         [
            4,
            "64653a20"
         ]
      ],
      [
         "RO",
         [
            2,
            "7765"
         ]
      ],
      [
         "RO",
         [
            5,
            "62736f636b"
         ]
      ],
      [
         "RO",
         [
            1,
            "65"
         ]
      ],
      [
         "RO",
         [
            10,
            "740d0a436f6e6e656374"
         ]
      ],
      [
         "RO",
         [
            64,
            "696f6e3a20557067726164650d0a5365632d576562536f636b65742d4163636570743a207030675546334a4231504b3468653552446959516b614c335359413d ..."
         ]
      ],
      [
         "RO",
         [
            4,
            "0d0a0d0a"
         ]
      ],
      [
         "TF",
         [
            13,
            "Hello, world!"
         ],
         1,
         true,
         0,
         "523235f8",
         null,
         null,
         false
      ],
      [
         "TO",
         [
            19,
            "818d523235f81a5759943d1e158f3d40599c73"
         ],
         false
      ],
      [
         "TF",
         [
            0,
            ""
         ],
         5,
         true,
         0,
         "fa946a58",
         null,
         null,
         false
      ],
      [
         "TO",
         [
            6,
            "8580fa946a58"
         ],
         false
      ],
      [
         "TF",
         [
            0,
            ""
         ],
         9,
         true,
         0,
         "a0303c50",
         null,
         null,
         false
      ],
      [
         "TO",
         [
            6,
            "8980a0303c50"
         ],
         false
      ],
      [
         "KL",
         1
      ],
      [
         "RO",
         [
            15,
            "810d48656c6c6f2c20776f726c6421"
         ]
      ],
      [
         "RF",
         [
            13,
            "Hello, world!"
         ],
         1,
         true,
         0,
         false,
         null
      ],
      [
         "RO",
         [
            4,
            "880203ea"
         ]
      ],
      [
         "RF",
         [
            2,
            "0x03ea"
         ],
         8,
         true,
         0,
         false,
         null
      ],
      [
         "TF",
         [
            2,
            "0x03e8"
         ],
         8,
         true,
         0,
         "65c405ce",
         null,
         null,
         false
      ],
      [
         "TO",
         [
            8,
            "888265c405ce662c"
         ],
         false
      ]
   ]
}