{
   "agent": "AVR / W5100 / Ethernet",
   "behavior": "OK",
   "behaviorClose": "OK",
   "case": 23,
   "closedByMe": true,
   "createStats": true,
   "createWirelog": true,
   "description": "Send unsolicited pong without payload. Verify nothing is received. Clean close with normal code.",
   "droppedByMe": false,
   "duration": 8,
   "expectation": "Nothing.",
   "expected": {
      "OK": []
   },
   "expectedClose": {
      "closeCode": [
         1000
      ],
      "closedByMe": true,
      "requireClean": true
   },
   "failedByMe": false,
   "httpRequest": "GET / HTTP/1.1\r\nUser-Agent: AutobahnTestSuite/0.8.0-0.10.9\r\nHost: 192.168.46.141:9001\r\nUpgrade: WebSocket\r\nConnection: Upgrade\r\nPragma: no-cache\r\nCache-Control: no-cache\r\nSec-WebSocket-Key: VHYYBlmDZxnY22tgBH7gtw==\r\nSec-WebSocket-Version: 13\r\n\r\n",
   "httpResponse": "HTTP/1.1 101 Switching Protocols\r\nUpgrade: websocket\r\nConnection: Upgrade\r\nSec-WebSocket-Accept: pn0BCAU/wp2P4bEaKc/3x8HnZAE=\r\n\r\n",
   "id": "2.7",
   "isServer": false,
   "localCloseCode": 1000,
   "localCloseReason": null,
   "received": [],
   "remoteCloseCode": 1000,
   "remoteCloseReason": null,
   "reportCompressionRatio": false,
   "reportTime": false,
   "result": "Actual events match at least one expected.",
   "resultClose": "Connection was properly closed",
   "rxFrameStats": {
      "8": 1
   },
   "rxOctetStats": {
      "1": 17,
      "2": 11,
      "3": 7,
      "4": 4,
      "5": 1,
      "52": 1
   },
   "started": "2019-03-22T21:13:22.373Z",
   "trafficStats": null,
   "txFrameStats": {
      "8": 1,
      "10": 1
   },
   "txOctetStats": {
      "6": 1,
      "8": 1,
      "245": 1
   },
   "wasClean": true,
   "wasCloseHandshakeTimeout": false,
   "wasNotCleanReason": null,
   "wasOpenHandshakeTimeout": false,
   "wasServerConnectionDropTimeout": false,
   "wirelog": [
      [
         "TO",
         [
            245,
            "474554202f20485454502f312e310d0a557365722d4167656e743a204175746f6261686e5465737453756974652f302e382e302d302e31302e390d0a486f7374 ..."
         ],
         false
      ],
      [
         "RO",
         [
            1,
            "48"
         ]
      ],
      [
         "RO",
         [
            2,
            "5454"
         ]
      ],
      [
         "RO",
         [
            1,
            "50"
         ]
      ],
      [
         "RO",
         [
            2,
            "2f31"
         ]
      ],
      [
         "RO",
         [
            2,
            "2e31"
         ]
      ],
      [
         "RO",
         [
            2,
            "2031"
         ]
      ],
      [
         "RO",
         [
            2,
            "3031"
         ]
      ],
      [
         "RO",
         [
            3,
            "205377"
         ]
      ],
      [
         "RO",
         [
            1,
            "69"
         ]
      ],
      [
         "RO",
         [
            1,
            "74"
         ]
      ],
      [
         "RO",
         [
            3,
            "636869"
         ]
      ],
      [
         "RO",
         [
            1,
            "6e"
         ]
      ],
      [
         "RO",
         [
            1,
            "67"
         ]
      ],
      [
         "RO",
         [
            1,
            "20"
         ]
      ],
      [
         "RO",
         [
            1,
            "50"
         ]
      ],
      [
         "RO",
         [
            1,
            "72"
         ]
      ],
      [
         "RO",
         [
            1,
            "6f"
         ]
      ],
      [
         "RO",
         [
            3,
            "746f63"
         ]
      ],
      [
         "RO",
         [
            3,
            "6f6c73"
         ]
      ],
      [
         "RO",
         [
            4,
            "0d0a5570"
         ]
      ],
      [
         "RO",
         [
            2,
            "6772"
         ]
      ],
      [
         "RO",
         [
            2,
            "6164"
         ]
      ],
      [
         "RO",
         [
            1,
            "65"
         ]
      ],
      [
         "RO",
         [
            3,
            "3a2077"
         ]
      ],
      [
         "RO",
         [
            1,
            "65"
         ]
      ],
      [
         "RO",
         [
            2,
            "6273"
         ]
      ],
      [
         "RO",
         [
            1,
            "6f"
         ]
      ],
      [
         "RO",
         [
            1,
            "63"
         ]
      ],
      [
         "RO",
         [
            2,
            "6b65"
         ]
      ],
      [
         "RO",
         [
            3,
            "740d0a"
         ]
      ],
      [
         "RO",
         [
            1,
            "43"
         ]
      ],
      [
         "RO",
         [
            1,
            "6f"
         ]
      ],
      [
         "RO",
         [
            2,
            "6e6e"
         ]
      ],
      [
         "RO",
         [
            1,
            "65"
         ]
      ],
      [
         "RO",
         [
            4,
            "6374696f"
         ]
      ],
      [
         "RO",
         [
            5,
            "6e3a205570"
         ]
      ],
      [
         "RO",
         [
            3,
            "677261"
         ]
      ],
      [
         "RO",
         [
            4,
            "64650d0a"
         ]
      ],
      [
         "RO",
         [
            52,
            "5365632d576562536f636b65742d4163636570743a20706e30424341552f77703250346245614b632f337838486e5a41453d0d0a"
         ]
      ],
      [
         "RO",
         [
            2,
            "0d0a"
         ]
      ],
      [
         "TF",
         [
            0,
            ""
         ],
         10,
         true,
         0,
         "6eef8e6a",
         null,
         null,
         false
      ],
      [
         "TO",
         [
            6,
            "8a806eef8e6a"
         ],
         false
      ],
      [
         "TF",
         [
            2,
            "0x03e8"
         ],
         8,
         true,
         0,
         "6fcd1fc7",
         null,
         null,
         false
      ],
      [
         "TO",
         [
            8,
            "88826fcd1fc76c25"
         ],
         false
      ],
      [
         "TI",
         1
      ],
      [
         "RO",
         [
            4,
            "880203e8"
         ]
      ],
      [
         "RF",
         [
            2,
            "0x03e8"
         ],
         8,
         true,
         0,
         false,
         null
      ]
   ]
}