{
   "agent": "AVR / W5100 / Ethernet",
   "behavior": "OK",
   "behaviorClose": "OK",
   "case": 111,
   "closedByMe": false,
   "createStats": true,
   "createWirelog": true,
   "description": "Send a text message with payload which is not valid UTF-8 in one fragment.<br><br>Payload: 0xf4908080",
   "droppedByMe": false,
   "duration": 4,
   "expectation": "The connection is failed immediately, since the payload is not valid UTF-8.",
   "expected": {
      "OK": []
   },
   "expectedClose": {
      "closeCode": [
         1007
      ],
      "closedByMe": false,
      "closedByWrongEndpointIsFatal": true,
      "requireClean": false
   },
   "failedByMe": false,
   "httpRequest": "GET / HTTP/1.1\r\nUser-Agent: AutobahnTestSuite/0.8.0-0.10.9\r\nHost: 192.168.46.180:9001\r\nUpgrade: WebSocket\r\nConnection: Upgrade\r\nPragma: no-cache\r\nCache-Control: no-cache\r\nSec-WebSocket-Key: HujkZX0F7xcybE6w2wJAOg==\r\nSec-WebSocket-Version: 13\r\n\r\n",
   "httpResponse": "HTTP/1.1 101 Switching Protocols\r\nUpgrade: websocket\r\nConnection: Upgrade\r\nSec-WebSocket-Accept: gtCeRWxu1l0q5y0qo6v8k7r39TY=\r\n\r\n",
   "id": "6.11.5",
   "isServer": false,
   "localCloseCode": 1000,
   "localCloseReason": null,
   "received": [],
   "remoteCloseCode": 1007,
   "remoteCloseReason": null,
   "reportCompressionRatio": false,
   "reportTime": false,
   "result": "Actual events match at least one expected.",
   "resultClose": "Connection was properly closed",
   "rxFrameStats": {
      "8": 1
   },
   "rxOctetStats": {
      "1": 47,
      "2": 12,
      "3": 4,
      "50": 1
   },
   "started": "2020-06-03T17:01:24.904Z",
   "trafficStats": null,
   "txFrameStats": {
      "1": 1,
      "8": 1
   },
   "txOctetStats": {
      "8": 1,
      "10": 1,
      "245": 1
   },
   "wasClean": true,
   "wasCloseHandshakeTimeout": false,
   "wasNotCleanReason": null,
   "wasOpenHandshakeTimeout": false,
   "wasServerConnectionDropTimeout": false,
   "wirelog": [
      [
         "TO",
         [
            245,
            "474554202f20485454502f312e310d0a557365722d4167656e743a204175746f6261686e5465737453756974652f302e382e302d302e31302e390d0a486f7374 ..."
         ],
         false
      ],
      [
         "RO",
         [
            1,
            "48"
         ]
      ],
      [
         "RO",
         [
            2,
            "5454"
         ]
      ],
      [
         "RO",
         [
            1,
            "50"
         ]
      ],
      [
         "RO",
         [
            1,
            "2f"
         ]
      ],
      [
         "RO",
         [
            2,
            "312e"
         ]
      ],
      [
         "RO",
         [
            1,
            "31"
         ]
      ],
      [
         "RO",
         [
            1,
            "20"
         ]
      ],
      [
         "RO",
         [
            1,
            "31"
         ]
      ],
      [
         "RO",
         [
            2,
            "3031"
         ]
      ],
      [
         "RO",
         [
            1,
            "20"
         ]
      ],
      [
         "RO",
         [
            1,
            "53"
         ]
      ],
      [
         "RO",
         [
            1,
            "77"
         ]
      ],
      [
         "RO",
         [
            3,
            "697463"
         ]
      ],
      [
         "RO",
         [
            1,
            "68"
         ]
      ],
      [
         "RO",
         [
            1,
            "69"
         ]
      ],
      [
         "RO",
         [
            1,
            "6e"
         ]
      ],
      [
         "RO",
         [
            1,
            "67"
         ]
      ],
      [
         "RO",
         [
            3,
            "205072"
         ]
      ],
      [
         "RO",
         [
            2,
            "6f74"
         ]
      ],
      [
         "RO",
         [
            1,
            "6f"
         ]
      ],
      [
         "RO",
         [
            1,
            "63"
         ]
      ],
      [
         "RO",
         [
            1,
            "6f"
         ]
      ],
      [
         "RO",
         [
            1,
            "6c"
         ]
      ],
      [
         "RO",
         [
            1,
            "73"
         ]
      ],
      [
         "RO",
         [
            2,
            "0d0a"
         ]
      ],
      [
         "RO",
         [
            2,
            "5570"
         ]
      ],
      [
         "RO",
         [
            1,
            "67"
         ]
      ],
      [
         "RO",
         [
            1,
            "72"
         ]
      ],
      [
         "RO",
         [
            1,
            "61"
         ]
      ],
      [
         "RO",
         [
            1,
            "64"
         ]
      ],
      [
         "RO",
         [
            1,
            "65"
         ]
      ],
      [
         "RO",
         [
            1,
            "3a"
         ]
      ],
      [
         "RO",
         [
            1,
            "20"
         ]
      ],
      [
         "RO",
         [
            1,
            "77"
         ]
      ],
      [
         "RO",
         [
            1,
            "65"
         ]
      ],
      [
         "RO",
         [
            1,
            "62"
         ]
      ],
      [
         "RO",
         [
            1,
            "73"
         ]
      ],
      [
         "RO",
         [
            1,
            "6f"
         ]
      ],
      [
         "RO",
         [
            1,
            "63"
         ]
      ],
      [
         "RO",
         [
            1,
            "6b"
         ]
      ],
      [
         "RO",
         [
            1,
            "65"
         ]
      ],
      [
         "RO",
         [
            1,
            "74"
         ]
      ],
      [
         "RO",
         [
            2,
            "0d0a"
         ]
      ],
      [
         "RO",
         [
            1,
            "43"
         ]
      ],
      [
         "RO",
         [
            1,
            "6f"
         ]
      ],
      [
         "RO",
         [
            1,
            "6e"
         ]
      ],
      [
         "RO",
         [
            1,
            "6e"
         ]
      ],
      [
         "RO",
         [
            1,
            "65"
         ]
      ],
      [
         "RO",
         [
            1,
            "63"
         ]
      ],
      [
         "RO",
         [
            1,
            "74"
         ]
      ],
      [
         "RO",
         [
            1,
            "69"
         ]
      ],
      [
         "RO",
         [
            1,
            "6f"
         ]
      ],
      [
         "RO",
         [
            3,
            "6e3a20"
         ]
      ],
      [
         "RO",
         [
            3,
            "557067"
         ]
      ],
      [
         "RO",
         [
            1,
            "72"
         ]
      ],
      [
         "RO",
         [
            1,
            "61"
         ]
      ],
      [
         "RO",
         [
            1,
            "64"
         ]
      ],
      [
         "RO",
         [
            1,
            "65"
         ]
      ],
      [
         "RO",
         [
            2,
            "0d0a"
         ]
      ],
      [
         "RO",
         [
            50,
            "5365632d576562536f636b65742d4163636570743a206774436552577875316c3071357930716f3676386b3772333954593d"
         ]
      ],
      [
         "RO",
         [
            2,
            "0d0a"
         ]
      ],
      [
         "RO",
         [
            2,
            "0d0a"
         ]
      ],
      [
         "TF",
         [
            4,
            "0xf4908080"
         ],
         1,
         true,
         0,
         "3089f3a8",
         null,
         null,
         false
      ],
      [
         "TO",
         [
            10,
            "81843089f3a8c4197328"
         ],
         false
      ],
      [
         "KL",
         0.5
      ],
      [
         "RO",
         [
            2,
            "8802"
         ]
      ],
      [
         "RO",
         [
            2,
            "03ef"
         ]
      ],
      [
         "RF",
         [
            2,
            "0x03ef"
         ],
         8,
         true,
         0,
         false,
         null
      ],
      [
         "TF",
         [
            2,
            "0x03e8"
         ],
         8,
         true,
         0,
         "dc5afbc8",
         null,
         null,
         false
      ],
      [
         "TO",
         [
            8,
            "8882dc5afbc8dfb2"
         ],
         false
      ]
   ]
}