{
   "agent": "ESP8266 / WiFi",
   "behavior": "OK",
   "behaviorClose": "OK",
   "case": 23,
   "closedByMe": true,
   "createStats": true,
   "createWirelog": true,
   "description": "Send unsolicited pong without payload. Verify nothing is received. Clean close with normal code.",
   "droppedByMe": false,
   "duration": 111,
   "expectation": "Nothing.",
   "expected": {
      "OK": []
   },
   "expectedClose": {
      "closeCode": [
         1000
      ],
      "closedByMe": true,
      "requireClean": true
   },
   "failedByMe": false,
   "httpRequest": "GET / HTTP/1.1\r\nUser-Agent: AutobahnTestSuite/0.8.0-0.10.9\r\nHost: 192.168.46.126:9001\r\nUpgrade: WebSocket\r\nConnection: Upgrade\r\nPragma: no-cache\r\nCache-Control: no-cache\r\nSec-WebSocket-Key: Zk3ZqUgyZ+Chui+lcK53Yw==\r\nSec-WebSocket-Version: 13\r\n\r\n",
   "httpResponse": "HTTP/1.1 101 Switching Protocols\r\nUpgrade: websocket\r\nConnection: Upgrade\r\nSec-WebSocket-Accept: LkZ0BW5F3G1IWBHFPcNwpo0mLdU=\r\n\r\n",
   "id": "2.7",
   "isServer": false,
   "localCloseCode": 1000,
   "localCloseReason": null,
   "received": [],
   "remoteCloseCode": 1000,
   "remoteCloseReason": null,
   "reportCompressionRatio": false,
   "reportTime": false,
   "result": "Actual events match at least one expected.",
   "resultClose": "Connection was properly closed",
   "rxFrameStats": {
      "8": 1
   },
   "rxOctetStats": {
      "1": 7,
      "2": 8,
      "3": 5,
      "4": 4,
      "5": 2,
      "7": 1,
      "8": 1,
      "54": 1
   },
   "started": "2019-03-22T21:12:30.987Z",
   "trafficStats": null,
   "txFrameStats": {
      "8": 1,
      "10": 1
   },
   "txOctetStats": {
      "6": 1,
      "8": 1,
      "245": 1
   },
   "wasClean": true,
   "wasCloseHandshakeTimeout": false,
   "wasNotCleanReason": null,
   "wasOpenHandshakeTimeout": false,
   "wasServerConnectionDropTimeout": false,
   "wirelog": [
      [
         "TO",
         [
            245,
            "474554202f20485454502f312e310d0a557365722d4167656e743a204175746f6261686e5465737453756974652f302e382e302d302e31302e390d0a486f7374 ..."
         ],
         false
      ],
      [
         "RO",
         [
            3,
            "485454"
         ]
      ],
      [
         "RO",
         [
            1,
            "50"
         ]
      ],
      [
         "RO",
         [
            1,
            "2f"
         ]
      ],
      [
         "RO",
         [
            3,
            "312e31"
         ]
      ],
      [
         "RO",
         [
            4,
            "20313031"
         ]
      ],
      [
         "RO",
         [
            1,
            "20"
         ]
      ],
      [
         "RO",
         [
            3,
            "537769"
         ]
      ],
      [
         "RO",
         [
            8,
            "746368696e672050"
         ]
      ],
      [
         "RO",
         [
            1,
            "72"
         ]
      ],
      [
         "RO",
         [
            2,
            "6f74"
         ]
      ],
      [
         "RO",
         [
            2,
            "6f63"
         ]
      ],
      [
         "RO",
         [
            1,
            "6f"
         ]
      ],
      [
         "RO",
         [
            4,
            "6c730d0a"
         ]
      ],
      [
         "RO",
         [
            2,
            "5570"
         ]
      ],
      [
         "RO",
         [
            1,
            "67"
         ]
      ],
      [
         "RO",
         [
            2,
            "7261"
         ]
      ],
      [
         "RO",
         [
            2,
            "6465"
         ]
      ],
      [
         "RO",
         [
            4,
            "3a207765"
         ]
      ],
      [
         "RO",
         [
            2,
            "6273"
         ]
      ],
      [
         "RO",
         [
            7,
            "6f636b65740d0a"
         ]
      ],
      [
         "RO",
         [
            1,
            "43"
         ]
      ],
      [
         "RO",
         [
            2,
            "6f6e"
         ]
      ],
      [
         "RO",
         [
            5,
            "6e65637469"
         ]
      ],
      [
         "RO",
         [
            3,
            "6f6e3a"
         ]
      ],
      [
         "RO",
         [
            3,
            "205570"
         ]
      ],
      [
         "RO",
         [
            2,
            "6772"
         ]
      ],
      [
         "RO",
         [
            5,
            "6164650d0a"
         ]
      ],
      [
         "RO",
         [
            54,
            "5365632d576562536f636b65742d4163636570743a204c6b5a3042573546334731495742484650634e77706f306d4c64553d0d0a0d0a"
         ]
      ],
      [
         "TF",
         [
            0,
            ""
         ],
         10,
         true,
         0,
         "b80979da",
         null,
         null,
         false
      ],
      [
         "TO",
         [
            6,
            "8a80b80979da"
         ],
         false
      ],
      [
         "TF",
         [
            2,
            "0x03e8"
         ],
         8,
         true,
         0,
         "c4b8f7ae",
         null,
         null,
         false
      ],
      [
         "TO",
         [
            8,
            "8882c4b8f7aec750"
         ],
         false
      ],
      [
         "TI",
         1
      ],
      [
         "RO",
         [
            4,
            "880203e8"
         ]
      ],
      [
         "RF",
         [
            2,
            "0x03e8"
         ],
         8,
         true,
         0,
         false,
         null
      ]
   ]
}