{
   "agent": "ESP8266 / WiFi",
   "behavior": "OK",
   "behaviorClose": "OK",
   "case": 45,
   "closedByMe": false,
   "createStats": true,
   "createWirelog": true,
   "description": "Send Ping fragmented into 2 fragments.",
   "droppedByMe": false,
   "duration": 110,
   "expectation": "Connection is failed immediately, since control message MUST NOT be fragmented.",
   "expected": {
      "OK": []
   },
   "expectedClose": {
      "closeCode": [
         1002
      ],
      "closedByMe": false,
      "requireClean": false
   },
   "failedByMe": false,
   "httpRequest": "GET / HTTP/1.1\r\nUser-Agent: AutobahnTestSuite/0.8.0-0.10.9\r\nHost: 192.168.46.126:9001\r\nUpgrade: WebSocket\r\nConnection: Upgrade\r\nPragma: no-cache\r\nCache-Control: no-cache\r\nSec-WebSocket-Key: tkx3g6lMm/JsdZPDcrT2Lw==\r\nSec-WebSocket-Version: 13\r\n\r\n",
   "httpResponse": "HTTP/1.1 101 Switching Protocols\r\nUpgrade: websocket\r\nConnection: Upgrade\r\nSec-WebSocket-Accept: +49Y40iPtrxDuCugc5zHzHipeJM=\r\n\r\n",
   "id": "5.1",
   "isServer": false,
   "localCloseCode": 1000,
   "localCloseReason": null,
   "received": [],
   "remoteCloseCode": 1002,
   "remoteCloseReason": null,
   "reportCompressionRatio": false,
   "reportTime": false,
   "result": "Actual events match at least one expected.",
   "resultClose": "Connection was properly closed",
   "rxFrameStats": {
      "8": 1
   },
   "rxOctetStats": {
      "1": 6,
      "2": 8,
      "3": 5,
      "4": 4,
      "5": 1,
      "7": 3,
      "54": 1
   },
   "started": "2019-03-22T21:12:37.598Z",
   "trafficStats": null,
   "txFrameStats": {
      "0": 1,
      "8": 1,
      "9": 1
   },
   "txOctetStats": {
      "8": 1,
      "15": 2,
      "245": 1
   },
   "wasClean": true,
   "wasCloseHandshakeTimeout": false,
   "wasNotCleanReason": null,
   "wasOpenHandshakeTimeout": false,
   "wasServerConnectionDropTimeout": false,
   "wirelog": [
      [
         "TO",
         [
            245,
            "474554202f20485454502f312e310d0a557365722d4167656e743a204175746f6261686e5465737453756974652f302e382e302d302e31302e390d0a486f7374 ..."
         ],
         false
      ],
      [
         "RO",
         [
            1,
            "48"
         ]
      ],
      [
         "RO",
         [
            7,
            "5454502f312e31"
         ]
      ],
      [
         "RO",
         [
            2,
            "2031"
         ]
      ],
      [
         "RO",
         [
            1,
            "30"
         ]
      ],
      [
         "RO",
         [
            5,
            "3120537769"
         ]
      ],
      [
         "RO",
         [
            1,
            "74"
         ]
      ],
      [
         "RO",
         [
            2,
            "6368"
         ]
      ],
      [
         "RO",
         [
            3,
            "696e67"
         ]
      ],
      [
         "RO",
         [
            2,
            "2050"
         ]
      ],
      [
         "RO",
         [
            4,
            "726f746f"
         ]
      ],
      [
         "RO",
         [
            2,
            "636f"
         ]
      ],
      [
         "RO",
         [
            1,
            "6c"
         ]
      ],
      [
         "RO",
         [
            3,
            "730d0a"
         ]
      ],
      [
         "RO",
         [
            2,
            "5570"
         ]
      ],
      [
         "RO",
         [
            3,
            "677261"
         ]
      ],
      [
         "RO",
         [
            3,
            "64653a"
         ]
      ],
      [
         "RO",
         [
            2,
            "2077"
         ]
      ],
      [
         "RO",
         [
            4,
            "6562736f"
         ]
      ],
      [
         "RO",
         [
            4,
            "636b6574"
         ]
      ],
      [
         "RO",
         [
            7,
            "0d0a436f6e6e65"
         ]
      ],
      [
         "RO",
         [
            2,
            "6374"
         ]
      ],
      [
         "RO",
         [
            7,
            "696f6e3a205570"
         ]
      ],
      [
         "RO",
         [
            1,
            "67"
         ]
      ],
      [
         "RO",
         [
            4,
            "72616465"
         ]
      ],
      [
         "RO",
         [
            54,
            "0d0a5365632d576562536f636b65742d4163636570743a202b34395934306950747278447543756763357a487a486970654a4d3d0d0a"
         ]
      ],
      [
         "RO",
         [
            2,
            "0d0a"
         ]
      ],
      [
         "TF",
         [
            9,
            "fragment1"
         ],
         9,
         false,
         0,
         "61c9e8e3",
         null,
         null,
         false
      ],
      [
         "TO",
         [
            15,
            "098961c9e8e307bb89840cac869750"
         ],
         false
      ],
      [
         "TF",
         [
            9,
            "fragment2"
         ],
         0,
         true,
         0,
         "b0ce1a83",
         null,
         null,
         false
      ],
      [
         "TO",
         [
            15,
            "8089b0ce1a83d6bc7be4ddab74f782"
         ],
         false
      ],
      [
         "KL",
         1
      ],
      [
         "RO",
         [
            1,
            "88"
         ]
      ],
      [
         "RO",
         [
            3,
            "0203ea"
         ]
      ],
      [
         "RF",
         [
            2,
            "0x03ea"
         ],
         8,
         true,
         0,
         false,
         null
      ],
      [
         "TF",
         [
            2,
            "0x03e8"
         ],
         8,
         true,
         0,
         "0fe761bc",
         null,
         null,
         false
      ],
      [
         "TO",
         [
            8,
            "88820fe761bc0c0f"
         ],
         false
      ]
   ]
}