{
   "agent": "SAMD21 / W5100 / Ethernet",
   "behavior": "OK",
   "behaviorClose": "OK",
   "case": 19,
   "closedByMe": true,
   "createStats": true,
   "createWirelog": true,
   "description": "Send ping with small binary (non UTF-8) payload.",
   "droppedByMe": false,
   "duration": 29,
   "expectation": "Pong with payload echo'ed is sent in reply to Ping. Clean close with normal code.",
   "expected": {
      "OK": [
         [
            "pong",
            "0x00fffefdfcfb00ff"
         ]
      ]
   },
   "expectedClose": {
      "closeCode": [
         1000
      ],
      "closedByMe": true,
      "requireClean": true
   },
   "failedByMe": false,
   "httpRequest": "GET / HTTP/1.1\r\nUser-Agent: AutobahnTestSuite/0.8.0-0.10.9\r\nHost: 192.168.46.143:9001\r\nUpgrade: WebSocket\r\nConnection: Upgrade\r\nPragma: no-cache\r\nCache-Control: no-cache\r\nSec-WebSocket-Key: LUUTmPjXXs0KrCm/1LuqWA==\r\nSec-WebSocket-Version: 13\r\n\r\n",
   "httpResponse": "HTTP/1.1 101 Switching Protocols\r\nUpgrade: websocket\r\nConnection: Upgrade\r\nSec-WebSocket-Accept: 3P6ojrmrKsVoP6njZY+0VCryjy4=\r\n\r\n",
   "id": "2.3",
   "isServer": false,
   "localCloseCode": 1000,
   "localCloseReason": null,
   "received": [
      [
         "pong",
         "0x00fffefdfcfb00ff"
      ]
   ],
   "remoteCloseCode": 1000,
   "remoteCloseReason": null,
   "reportCompressionRatio": false,
   "reportTime": false,
   "result": "Actual events match at least one expected.",
   "resultClose": "Connection was properly closed",
   "rxFrameStats": {
      "8": 1,
      "10": 1
   },
   "rxOctetStats": {
      "1": 1,
      "2": 1,
      "4": 1,
      "9": 1,
      "20": 1,
      "21": 1,
      "32": 1,
      "54": 1
   },
   "started": "2019-03-22T21:13:11.742Z",
   "trafficStats": null,
   "txFrameStats": {
      "8": 1,
      "9": 1
   },
   "txOctetStats": {
      "8": 1,
      "14": 1,
      "245": 1
   },
   "wasClean": true,
   "wasCloseHandshakeTimeout": false,
   "wasNotCleanReason": null,
   "wasOpenHandshakeTimeout": false,
   "wasServerConnectionDropTimeout": false,
   "wirelog": [
      [
         "TO",
         [
            245,
            "474554202f20485454502f312e310d0a557365722d4167656e743a204175746f6261686e5465737453756974652f302e382e302d302e31302e390d0a486f7374 ..."
         ],
         false
      ],
      [
         "RO",
         [
            32,
            "485454502f312e312031303120537769746368696e672050726f746f636f6c73"
         ]
      ],
      [
         "RO",
         [
            20,
            "0d0a557067726164653a20776562736f636b6574"
         ]
      ],
      [
         "RO",
         [
            2,
            "0d0a"
         ]
      ],
      [
         "RO",
         [
            21,
            "436f6e6e656374696f6e3a20557067726164650d0a"
         ]
      ],
      [
         "RO",
         [
            54,
            "5365632d576562536f636b65742d4163636570743a203350366f6a726d724b73566f50366e6a5a592b30564372796a79343d0d0a0d0a"
         ]
      ],
      [
         "TF",
         [
            8,
            "0x00fffefdfcfb00ff"
         ],
         9,
         true,
         0,
         "fa4c5813",
         null,
         null,
         false
      ],
      [
         "TO",
         [
            14,
            "8988fa4c5813fab3a6ee06b758ec"
         ],
         false
      ],
      [
         "TI",
         1
      ],
      [
         "RO",
         [
            1,
            "8a"
         ]
      ],
      [
         "RO",
         [
            9,
            "0800fffefdfcfb00ff"
         ]
      ],
      [
         "RF",
         [
            8,
            "0x00fffefdfcfb00ff"
         ],
         10,
         true,
         0,
         false,
         null
      ],
      [
         "TF",
         [
            2,
            "0x03e8"
         ],
         8,
         true,
         0,
         "71d3c87d",
         null,
         null,
         false
      ],
      [
         "TO",
         [
            8,
            "888271d3c87d723b"
         ],
         false
      ],
      [
         "RO",
         [
            4,
            "880203e8"
         ]
      ],
      [
         "RF",
         [
            2,
            "0x03e8"
         ],
         8,
         true,
         0,
         false,
         null
      ]
   ]
}